stripenn/ImageProcessing.py
stripenn/__init__.py
stripenn/cli.py
stripenn/getStripe.py
stripenn/observed_over_expected.py
stripenn/score.py
stripenn/seeimage.py
stripenn/stats.py
stripenn/stripenn.py
stripenn-1.1.65.20.dist-info/METADATA
stripenn-1.1.65.20.dist-info/WHEEL
stripenn-1.1.65.20.dist-info/entry_points.txt
stripenn-1.1.65.20.dist-info/RECORD
