Metadata-Version: 2.1
Name: stripenn
Version: 1.1.65.20
Summary: Image-processing based detection of architectural stripes from chromatin conformation data
Author: Sora Yoon
Author-email: sora.yoon@pennmedicine.upenn.edu
Classifier: Programming Language :: Python :: 2
Classifier: Programming Language :: Python :: 2.7
Classifier: Programming Language :: Python :: 3
Classifier: Programming Language :: Python :: 3.4
Classifier: Programming Language :: Python :: 3.5
Classifier: Programming Language :: Python :: 3.6
Classifier: Programming Language :: Python :: 3.7
Classifier: Programming Language :: Python :: 3.8
Classifier: Programming Language :: Python :: 3.9
Classifier: Programming Language :: Python :: 3.10
Classifier: Programming Language :: Python :: 3.11
Requires-Dist: cooler
Requires-Dist: joblib
Requires-Dist: matplotlib
Requires-Dist: numpy
Requires-Dist: opencv-python
Requires-Dist: pandas
Requires-Dist: scikit-image
Requires-Dist: scipy
Requires-Dist: tqdm
Requires-Dist: typer
